fasttk/__init__.py
fasttk/__main__.py
fasttk/aworker.py
fasttk/base.py
fasttk/dev.py
fasttk/style.py
fasttk/tkvm.py
fasttk/tools.py
fasttk/_example/__init__.py
fasttk/nodes/__init__.py
fasttk/nodes/button.py
fasttk/nodes/canvas.py
fasttk/nodes/checkbutton.py
fasttk/nodes/combobox.py
fasttk/nodes/entry.py
fasttk/nodes/frame.py
fasttk/nodes/label.py
fasttk/nodes/radiobutton.py
fasttk/nodes/scale.py
fasttk/nodes/scrollbar.py
fasttk/nodes/spinbox.py
fasttk/nodes/text.py
fasttk/nodes/treeview.py
fasttk-0.2.9.dist-info/licenses/LICENSE
fasttk-0.2.9.dist-info/METADATA
fasttk-0.2.9.dist-info/WHEEL
fasttk-0.2.9.dist-info/entry_points.txt
fasttk-0.2.9.dist-info/top_level.txt
fasttk-0.2.9.dist-info/RECORD
