Metadata-Version: 2.4
Name: fasttk
Version: 0.2.9
Summary: Build user interface with tkinter in a simple and fast way.
Author-email: Darksky <darkskyx@foxmail.com>
Project-URL: Homepage, https://github.com/DarkskyX15/fasttk
Classifier: Programming Language :: Python :: 3
Classifier: Operating System :: OS Independent
Requires-Python: >=3.10
License-File: LICENSE
Requires-Dist: pillow>=11.2.1
Requires-Dist: watchfiles>=1.0.5
Dynamic: license-file
